[
  {
    "name": "Combat Fury (AA Example)",
    "type": "feat",
    "img": "icons/skills/melee/strike-sword-dagger-blue.webp",
    "system": {},
    "effects": [
      {
        "_id": "ae_combat_fury",
        "name": "Combat Fury (AA)",
        "icon": "icons/skills/melee/strike-sword-dagger-blue.webp",
        "disabled": false,
        "duration": {
          "seconds": null
        },
        "changes": [
          {
            "key": "flags.eq5e.combat.attackBonus",
            "mode": 2,
            "value": "1",
            "priority": 20
          }
        ],
        "flags": {
          "eq5e": {}
        }
      }
    ],
    "flags": {
      "eq5e": {
        "aa": {
          "aaId": "aa.combat-fury",
          "cost": 3,
          "maxRank": 3,
          "rank": 0,
          "scales": {
            "attackBonusPerRank": 1
          },
          "prereq": {
            "minLevel": 10
          },
          "category": "Combat"
        }
      }
    }
  },
  {
    "name": "Spell Casting Fury (AA Example)",
    "type": "feat",
    "img": "icons/magic/fire/flame-jet-orange.webp",
    "system": {},
    "effects": [
      {
        "_id": "ae_spell_fury",
        "name": "Spell Fury (AA)",
        "icon": "icons/magic/fire/flame-jet-orange.webp",
        "disabled": false,
        "duration": {
          "seconds": null
        },
        "changes": [
          {
            "key": "flags.eq5e.spell.potencyMult",
            "mode": 2,
            "value": "0.05",
            "priority": 20
          }
        ],
        "flags": {
          "eq5e": {}
        }
      }
    ],
    "flags": {
      "eq5e": {
        "aa": {
          "aaId": "aa.spell-fury",
          "cost": 2,
          "maxRank": 5,
          "rank": 0,
          "scales": {
            "potencyMultPerRank": 0.05
          },
          "prereq": {
            "minLevel": 15,
            "requires": [
              {
                "aaId": "aa.combat-fury",
                "rank": 1
              }
            ]
          },
          "category": "Spell"
        }
      }
    }
  },
  {
    "name": "Quick Reflexes (AA Example)",
    "type": "feat",
    "img": "icons/skills/movement/feet-winged-sandals.webp",
    "system": {},
    "effects": [
      {
        "_id": "ae_quick_reflexes",
        "name": "Quick Reflexes (AA)",
        "icon": "icons/skills/movement/feet-winged-sandals.webp",
        "disabled": false,
        "duration": {
          "seconds": null
        },
        "changes": [
          {
            "key": "flags.eq5e.defense.acBonus",
            "mode": 2,
            "value": "1",
            "priority": 20
          }
        ],
        "flags": {
          "eq5e": {}
        }
      }
    ],
    "flags": {
      "eq5e": {
        "aa": {
          "aaId": "aa.quick-reflexes",
          "cost": 4,
          "maxRank": 2,
          "rank": 0,
          "scales": {
            "acBonusPerRank": 1
          },
          "prereq": {
            "minLevel": 20,
            "requires": [
              {
                "aaId": "aa.combat-fury",
                "rank": 2
              }
            ]
          },
          "category": "Utility"
        }
      }
    }
  }
]